Workbook

Sheet Scenario_Output
A1: Transactions | H1: Balances | M1: Monthly NR | N1: =P1/1200 -> 0.0083333333 | P1: 10 | Q1: =P1/100 -> 0.1 | R1: =Q1/360 -> 0.00027777778
A2: PD | B2: ED | C2: Transaction | D2: Component | E2: Amount | F2: Entry | H2: UPB | I2: AIR | M2: Daily NR | N2: =R1 -> 0.00027777778
A3: 44592 | B3: =A3 -> 44592 | C3: Purchase | D3: UPB | E3: 100000 | F3: New | H3: =E3 -> 100000 | I3: 0
A4: 44592 | B4: =A4 -> 44592 | C4: Purchase | D4: Interest | E4: 100 | F4: New | H4: =E3 -> 100000 | I4: =E4 -> 100 | M4: Monthly NR | N4: =P4/1200 -> 0.0125 | P4: 15 | Q4: =P4/100 -> 0.15 | R4: =Q4/360 -> 0.00041666667
A5: 44593 | B5: 44593 | C5: accrual | D5: Interest | E5: =H5*$N$2 -> 27.777778 | F5: New | H5: =H4 -> 100000 | I5: =I4+E5 -> 127.77778 | M5: Daily NR | N5: =R4 -> 0.00041666667
A6: 44594 | B6: 44594 | C6: accrual | D6: Interest | E6: =H6*$N$2 -> 27.777778 | F6: New | H6: =H5 -> 100000 | I6: =I5+E6 -> 155.55556
A7: 44595 | B7: 44595 | C7: Remit | E7: 210 | F7: New | H7: =H6 -> 100000 | I7: =I6 -> 155.55556
A8: 44595 | B8: 44595 | C8: Payment | D8: UPB | E8: =-(E7-I7) -> -54.444444 | F8: New | H8: =H7+E8 -> 99945.556 | I8: =I7 -> 155.55556
A9: 44595 | B9: 44595 | C9: Payment | D9: Interest | E9: =-(I8) -> -155.55556 | F9: New | H9: =H7+E8 -> 99945.556 | I9: =I8+E9 -> 0
A10: 44595 | B10: 44595 | C10: accrual | D10: Interest | E10: =H10*$N$2 -> 27.762654 | F10: New | H10: =H9 -> 99945.556 | I10: =E10+I9 -> 27.762654
A11: 44596 | B11: 44596 | C11: accrual | D11: Interest | E11: =ROUND(H10*N2,4) -> 27.7627 | F11: New | H11: =H10 -> 99945.556 | I11: =I10+E11 -> 55.525354
A12: 44597 | B12: 44597 | C12: accrual | D12: Interest | E12: =H10*$N$5 -> 41.643981 | F12: New | H12: =H11 -> 99945.556 | I12: =I11+E12 -> 97.169336

Sheet ORIG
A1: PostingDate | B1: EffectiveDate | C1: InstrumentId | D1: AttributeId | E1: ATTRIBUTE_LOAN_AMOUNT_CURRENT | F1: ATTRIBUTE_INTEREST_RECEIVABLE_CONSUMER_CURRENT

Sheet PMT
A1: PostingDate | B1: EffectiveDate | C1: InstrumentId | D1: AttributeId | E1: TRANSACTIONS_AMOUNT_REMIT

Sheet INT_ACC
A1: PostingDate | B1: EffectiveDate | C1: InstrumentId | D1: AttributeId | E1: ATTRIBUTE_INTEREST_RATE_CURRENT | F1: BALANCES_ENDINGBALANCE_Unpaid_Principal_Balance | G1: BALANCES_ENDINGBALANCE_Accrued_Interest_Receivable | H1: BALANCES_ENDINGBALANCE_Servicing_Interest_Accrual

Sheet RC
A1: PostingDate | B1: EffectiveDate | C1: InstrumentId | D1: AttributeId | E1: ATTRIBUTE_INTEREST_RATE_CURRENT | F1: ATTRIBUTE_INTEREST_RATE_PRIOR

Sheet CALCULATION
A1: PAYMENT CALC
A2: Interest Rate | B2: =IF('RC'!A2=CALCULATION!B4,'RC'!E2/100,INT_ACC!E2/100) -> 0 | D2: Purchased UPB | E2: =IF(ORIG!E2="",0,ORIG!E2) -> 0
A3: InstrumentId | B3: =INT_ACC!C2 -> 0 | D3: Purchased Interest | E3: =IF(ORIG!F2="",0,ORIG!F2) -> 0
A4: PostingDate | B4: =IF(INT_ACC!A2="","",(INT_ACC!A2))
A5: ReplayDate | B5: =IF(OR(MIN(PMT!$B$2:$B$13)=B4,MIN(PMT!$B$2:$B$13)=0),"",MIN(PMT!$B$2:$B$13))
A7: S.No | B7: Effective Date | C7: Beg UPB | D7: Beg AIR | E7: Days | F7: Final Remit | G7: Interest Paid | H7: Principal Paid | I7: End UPB | J7: Accrual | K7: End AIR
A8: 1 | B8: =B4 | C8: =INT_ACC!F2 -> 0 | D8: =INT_ACC!G2 -> 0 | E8: =IF(B8="","",IF(B9="",0,(B9-B8)-1)) | F8: =PMT!E2 -> 0 | G8: =IF(B8="","",IF(F8<D8,F8,D8)) | H8: =IF(B8="","",F8-G8) | I8: =IFERROR(IF(B8="","",C8-H8),0) | J8: =IFERROR(IF(B8="","",(I8*$B$2)/360),0) | K8: =IFERROR(IF(B8="","",D8-G8+J8),0)
G9: =IFERROR(IF(G8="",0,G8),0) -> 0 | H9: =IFERROR(IF(H8="",0,H8),0) -> 0 | I9: =IF(I8="",0,I8) -> 0 | J9: =IF(K8="",0,K8) -> 0
A12: ACCRUAL CALC
A13: S.No | B13: Effective Date | C13: Beg UPB | D13: Beg AIR | E13: Days | F13: Final Remit | G13: Interest Paid | H13: Principal Paid | I13: End UPB | J13: Accrual | K13: End AIR
A14: 1 | B14: =IF(INT_ACC!B2="","",INT_ACC!B2) | C14: =VALUE(INT_ACC!F2) -> 0 | D14: =VALUE(INT_ACC!G2) -> 0 | E14: =IF(B14="","",IF(B15="",0,(B15-B14)-1)) | F14: 0 | G14: =G9 -> 0 | H14: =H9 -> 0 | I14: =C14-H14 -> 0 | J14: =IF(B14="",0,(I14*$B$2)/360) -> 0 | K14: =D14+J14-G14 -> 0
A16: AIR Transactions
A17: Interest Accrual | B17: =J14 -> 0
A18: Interest Adjustment
A19: Interest Payment | B19: =G9 -> 0
A20: Purchased Interest | B20: =E3 -> 0
A22: UPB Transactions
A23: Principal Payment | B23: =H9 -> 0
A24: Principal Adjustment
A25: Purchased UPB | B25: =E2 -> 0
A27: Transactions
A28: PostingDate | B28: TransactionDate | C28: InstrumentId | D28: Transactiontype | E28: Amount | F28: AttributeId
A29: =IF(E2=0,B4,"") | B29: =A29 | C29: =IF(A29="","",$B$3) | D29: =IF(A29="","","Servicing_Interest_Accrual") | E29: =IF(A29="","",ROUND(B17,4)) | F29: =IF(A29="","",INT_ACC!$D$2)
A30: =IF(ROUND(B18,4)=0,"",$B$4) | B30: =IF(A30="","",A30) | C30: =IF(A30="","",$B$3) | D30: =IF(A30="","","Interest_Adjustment") | E30: =IF(A30="","",ROUND(B18,4)) | F30: =IF(A30="","",INT_ACC!$D$2)
A31: =IF(ROUND(B19,4)=0,"",$B$4) | B31: =IF(A31="","",A31) | C31: =IF(A31="","",$B$3) | D31: =IF(A31="","","Payment_Interest") | E31: =IF(A31="","",ROUND(B19,4)*-1) | F31: =IF(A31="","",INT_ACC!$D$2)
A32: =IF(ROUND(B23,4)=0,"",$B$4) | B32: =IF(A32="","",A32) | C32: =IF(A32="","",$B$3) | D32: =IF(A32="","","Payment_UPB") | E32: =IF(A32="","",ROUND(B23,4)*-1) | F32: =IF(A32="","",INT_ACC!$D$2)
A33: =IF(ROUND(B24,4)=0,"",$B$4) | B33: =IF(A33="","",A33) | C33: =IF(A33="","",$B$3) | D33: =IF(A33="","","Principal_Adjustment") | E33: =IF(A33="","",ROUND(B24,4)) | F33: =IF(A33="","",INT_ACC!$D$2)
A34: =IF(ROUND(B25,4)=0,"",$B$4) | B34: =IF(A34="","",A34) | C34: =IF(A34="","",$B$3) | D34: =IF(A34="","","Purchase_UPB") | E34: =IF(A34="","",ROUND(B25,4)) | F34: =IF(A34="","",INT_ACC!$D$2)
A35: =IF(ROUND(B20,4)=0,"",$B$4) | B35: =IF(A35="","",A35) | C35: =IF(A35="","",$B$3) | D35: =IF(A35="","","Purchase_Interest") | E35: =IF(A35="","",ROUND(B20,4)) | F35: =IF(A35="","",INT_ACC!$D$2)

Sheet EXPECTED_INP
A1: 44592
A2: ORIG
A3: PostingDate | B3: EffectiveDate | C3: InstrumentId | D3: AttributeId | E3: ATTRIBUTES_LOAN_AMOUNT_CURRENT | F3: ATTRIBUTES_INTEREST_RECEIVABLE_CONSUMER_CURRENT
A4: 44592 | B4: 44592 | C4: IDHJ-EGNY | D4: 1 | E4: 100000 | F4: 100
A6: INT_ACC
A7: PostingDate | B7: EffectiveDate | C7: InstrumentId | D7: AttributeId | E7: ATTRIBUTES_INTEREST_RATE_CURRENT | F7: BALANCES_BEGINNINGBALANCE_Unpaid_Principal_Balance | G7: BALANCES_BEGINNINGBALANCE_Accrued_Interest_Receivable | H7: BALANCES_BEGINNINGBALANCE_Servicing_Interest_Accrual
A8: 44592 | B8: 44592 | C8: IDHJ-EGNY | D8: 1 | E8: 10 | F8: 0 | G8: 0 | H8: 0
A11: 44593
B12: =TEXT(B15,"mm/dd/yyyy") -> 02/01/2022
A13: INT_ACC
A14: PostingDate | B14: EffectiveDate | C14: InstrumentId | D14: AttributeId | E14: ATTRIBUTES_INTEREST_RATE_CURRENT | F14: BALANCES_BEGINNINGBALANCE_Unpaid_Principal_Balance | G14: BALANCES_BEGINNINGBALANCE_Accrued_Interest_Receivable | H14: BALANCES_BEGINNINGBALANCE_Servicing_Interest_Accrual
A15: 02/01/2022 | B15: 02/01/2022 | C15: IDHJ-EGNY | D15: 1 | E15: 10 | F15: 100000 | G15: 100 | H15: 0
A18: 44594
A20: INT_ACC
A21: PostingDate | B21: EffectiveDate | C21: InstrumentId | D21: AttributeId | E21: ATTRIBUTES_INTEREST_RATE_CURRENT | F21: BALANCES_BEGINNINGBALANCE_Unpaid_Principal_Balance | G21: BALANCES_BEGINNINGBALANCE_Accrued_Interest_Receivable | H21: BALANCES_BEGINNINGBALANCE_Servicing_Interest_Accrual
A22: 44594 | B22: 44594 | C22: IDHJ-EGNY | D22: 1 | E22: 10 | F22: 100000 | G22: 127.7778 | H22: 27.7778
A25: 44595
A27: INT_ACC
A28: PostingDate | B28: EffectiveDate | C28: InstrumentId | D28: AttributeId | E28: ATTRIBUTES_INTEREST_RATE_CURRENT | F28: BALANCES_BEGINNINGBALANCE_Unpaid_Principal_Balance | G28: BALANCES_BEGINNINGBALANCE_Accrued_Interest_Receivable | H28: BALANCES_BEGINNINGBALANCE_Servicing_Interest_Accrual
A29: 44595 | B29: 44595 | C29: IDHJ-EGNY | D29: 1 | E29: 10 | F29: 100000 | G29: 155.5556 | H29: 55.5556
A31: PMT
A32: PostingDate | B32: EffectiveDate | C32: InstrumentId | D32: AttributeId | E32: TRANSACTIONS.AMOUNT.REMIT
A33: 44595 | B33: 44595 | C33: IDHJ-EGNY | D33: 1 | E33: 210
A36: 44596
A38: INT_ACC
A39: PostingDate | B39: EffectiveDate | C39: InstrumentId | D39: AttributeId | E39: ATTRIBUTES_INTEREST_RATE_CURRENT | F39: BALANCES_BEGINNINGBALANCE_Unpaid_Principal_Balance | G39: BALANCES_BEGINNINGBALANCE_Accrued_Interest_Receivable | H39: BALANCES_BEGINNINGBALANCE_Servicing_Interest_Accrual
A40: 44596 | B40: 44596 | C40: IDHJ-EGNY | D40: 1 | E40: 10 | F40: 99945.556 | G40: 27.7627 | H40: =H29+G40 -> 83.3183
A43: 44597
A45: INT_ACC
A46: PostingDate | B46: EffectiveDate | C46: InstrumentId | D46: AttributeId | E46: ATTRIBUTES_INTEREST_RATE_CURRENT | F46: BALANCES_BEGINNINGBALANCE_Unpaid_Principal_Balance | G46: BALANCES_BEGINNINGBALANCE_Accrued_Interest_Receivable | H46: BALANCES_BEGINNINGBALANCE_Servicing_Interest_Accrual
A47: 44597 | B47: 44597 | C47: IDHJ-EGNY | D47: 1 | E47: 10 | F47: 99945.556 | G47: 55.5254 | H47: 111.081
A49: RC
A50: PostingDate | B50: EffectiveDate | C50: InstrumentId | D50: AttributeId | E50: ATTRIBUTES_INTEREST_RATE_CURRENT | F50: ATTRIBUTES_INTEREST_RATE_PRIOR
A51: 44596 | B51: 44596 | C51: IDHJ-EGNY | D51: 1 | E51: 15 | F51: 10

Sheet Events
A1: INT_ACC
A3: Trigger Type
A4: ON MODEL EXECUTION
A6: Source Mapping
A7: Balances | B7: ENDINGBALANCE | C7: UPB,AIR,ACCRUAL
A8: Attribute | B8: NoteRate | C8: Current
A11: PMT
A13: Trigger Type | B13: Trigger Source
A14: ON TRANSACTION POST | B14: Remit
A17: Source Mapping
A18: Transactions | B18: Amount | C18: Remit
A20: ORIG
A21: Trigger Type
A22: ON ATTRIBUTE ADD
A24: Source Mapping
A25: Attribute | B25: Loan_amount | C25: Current
A26: Attribute | B26: INTEREST_RECEIVABLE_CONSUMER | C26: Current
A28: RC
A29: Trigger Type
A30: ON ATTRIBUTE CHANGE
A32: Source Mapping
A33: Attribute | B33: Interest Rate | C33: Current, Prior

Sheet o_Transaction
A1: PostingDate | B1: TransactionDate | C1: InstrumentId | D1: TransactionName | E1: Amount | F1: AttributeId
A2: =CALCULATION!A29 | B2: =CALCULATION!B29 | C2: =CALCULATION!C29 | D2: =CALCULATION!D29 | E2: =CALCULATION!E29 | F2: =CALCULATION!F29
A3: =CALCULATION!A30 | B3: =CALCULATION!B30 | C3: =CALCULATION!C30 | D3: =CALCULATION!D30 | E3: =CALCULATION!E30 | F3: =CALCULATION!F30
A4: =CALCULATION!A31 | B4: =CALCULATION!B31 | C4: =CALCULATION!C31 | D4: =CALCULATION!D31 | E4: =CALCULATION!E31 | F4: =CALCULATION!F31
A5: =CALCULATION!A32 | B5: =CALCULATION!B32 | C5: =CALCULATION!C32 | D5: =CALCULATION!D32 | E5: =CALCULATION!E32 | F5: =CALCULATION!F32
A6: =CALCULATION!A33 | B6: =CALCULATION!B33 | C6: =CALCULATION!C33 | D6: =CALCULATION!D33 | E6: =CALCULATION!E33 | F6: =CALCULATION!F33
A7: =CALCULATION!A34 | B7: =CALCULATION!B34 | C7: =CALCULATION!C34 | D7: =CALCULATION!D34 | E7: =CALCULATION!E34 | F7: =CALCULATION!F34
A8: =CALCULATION!A35 | B8: =CALCULATION!B35 | C8: =CALCULATION!C35 | D8: =CALCULATION!D35 | E8: =CALCULATION!E35 | F8: =CALCULATION!F35
